{
  "model": "opus",
  "date": "2026-06-15",
  "sport": "mlb",
  "logged_at": "2026-06-15T10:32:36Z",
  "picks": [
    {
      "game_id": "87cc10ad1f5377b838eb240a510a0f9f",
      "matchup": "MIA @ PHI",
      "away_abbr": "MIA",
      "home_abbr": "PHI",
      "action": "pass",
      "pick_raw": "PASS",
      "pick_side": null,
      "pick_market": null,
      "price": null,
      "units": 0,
      "units_raw": "PASS",
      "edge": "none",
      "reason": "Wheeler (2.89 xFIP, 25.6 K-BB%, Stf+109) is a genuine ace and PHI at -212 prices to ~68%, which is roughly fair given his dominance over Gusto's thin profile. The RL alternative at -102 needs PHI to win by 2 which their tepid offense doesn't reliably deliver. No projection gap on either side.",
      "data_gap": "Confirmed lineups; Gusto has only 83 AGG IP.",
      "result": null,
      "profit_units": 0.0,
      "clv": null,
      "closing_line": null,
      "parse_warning": null,
      "graded_at": "2026-06-16T09:06:08Z"
    },
    {
      "game_id": "fa294eb768832d8c8870b2c0559291c1",
      "matchup": "KC @ WAS",
      "away_abbr": "KC",
      "home_abbr": "WAS",
      "action": "pass",
      "pick_raw": "PASS",
      "pick_side": null,
      "pick_market": null,
      "price": null,
      "units": 0,
      "units_raw": "PASS",
      "edge": "none",
      "reason": "Spence (4.49/4.70 AGG, 9.8 K-BB%) vs Alvarez (3.84/4.09 but small sample and 6.2 BB/9 in L14) is a mediocre matchup both ways. WAS -141 prices ~58%, roughly where I land given home edge and superior offense. No 4-pt gap.",
      "data_gap": "Alvarez wildness trend; lineup confirmation.",
      "result": null,
      "profit_units": 0.0,
      "clv": null,
      "closing_line": null,
      "parse_warning": null,
      "graded_at": "2026-06-16T09:06:08Z"
    },
    {
      "game_id": "6b47a66c52d27dacd1c7bbcd808713c1",
      "matchup": "NYM @ CIN",
      "away_abbr": "NYM",
      "home_abbr": "CIN",
      "action": "pass",
      "pick_raw": "PASS",
      "pick_side": null,
      "pick_market": null,
      "price": null,
      "units": 0,
      "units_raw": "PASS",
      "edge": "none",
      "reason": "Burns (2.92 xFIP, 24.5 K-BB%, Stf+113) is a legit top arm and CIN -139 prices ~58%. Myers is weak (5.35 AGG xFIP, 4.9 K-BB%) which justifies the price; I have CIN around 56-58%, inside my no-bet band. CIN's brutal L10 (2-8) is narrative, not signal.",
      "data_gap": "Lineup confirmation.",
      "result": null,
      "profit_units": 0.0,
      "clv": null,
      "closing_line": null,
      "parse_warning": null,
      "graded_at": "2026-06-16T09:06:08Z"
    },
    {
      "game_id": "6dc67dec6b0c9f4a591f05d0f5912d23",
      "matchup": "SD @ STL",
      "away_abbr": "SD",
      "home_abbr": "STL",
      "action": "pass",
      "pick_raw": "PASS",
      "pick_side": null,
      "pick_market": null,
      "price": null,
      "units": 0,
      "units_raw": "PASS",
      "edge": "none",
      "reason": "Away starter TBD — automatic pass per data integrity rules. Cannot price without confirmed pitcher.",
      "data_gap": "SD starter identity.",
      "result": null,
      "profit_units": 0.0,
      "clv": null,
      "closing_line": null,
      "parse_warning": null,
      "graded_at": "2026-06-16T09:06:08Z"
    },
    {
      "game_id": "9c2784938a40031b48e75139185e2491",
      "matchup": "COL @ CHC",
      "away_abbr": "COL",
      "home_abbr": "CHC",
      "action": "pass",
      "pick_raw": "PASS",
      "pick_side": null,
      "pick_market": null,
      "price": null,
      "units": 0,
      "units_raw": "PASS",
      "edge": "none",
      "reason": "COL's road offense vs LHP is dreadful (68 wRC+) and Imanaga is fine, but CHC -204 prices ~67% and I land near there given Lorenzen's underlying form is better than his 7.54 ERA (4.31 AGG xFIP). RL at +100 is tempting but COL's +1.5 has held value all morning. No clean edge.",
      "data_gap": "Lineup confirmation.",
      "result": null,
      "profit_units": 0.0,
      "clv": null,
      "closing_line": null,
      "parse_warning": null,
      "graded_at": "2026-06-16T09:06:08Z"
    },
    {
      "game_id": "35d9a6cb5c11499a313b0205abf1c1f9",
      "matchup": "MIN @ TEX",
      "away_abbr": "MIN",
      "home_abbr": "TEX",
      "action": "pass",
      "pick_raw": "PASS",
      "pick_side": null,
      "pick_market": null,
      "price": null,
      "units": 0,
      "units_raw": "PASS",
      "edge": "none",
      "reason": "Away starter TBD — automatic pass. Gore is solid (3.87 AGG xFIP) but cannot price the game without MIN's arm.",
      "data_gap": "MIN starter identity.",
      "result": null,
      "profit_units": 0.0,
      "clv": null,
      "closing_line": null,
      "parse_warning": null,
      "graded_at": "2026-06-16T09:06:08Z"
    },
    {
      "game_id": "d5349ae869ae1b1c6c38042687a3e57b",
      "matchup": "DET @ HOU",
      "away_abbr": "DET",
      "home_abbr": "HOU",
      "action": "pass",
      "pick_raw": "PASS",
      "pick_side": null,
      "pick_market": null,
      "price": null,
      "units": 0,
      "units_raw": "PASS",
      "edge": "none",
      "reason": "Melton (2.81 ERA but 5.36 FIP, only 4.9 K/9, regression flag) vs Teng (4.49 AGG xFIP, ugly L14) is a coin-flip of mediocre arms. HOU -130 prices ~57%; I have it 54-57%, inside the band. Hader/King bullpen edge keeps me off DET. No qualifying gap.",
      "data_gap": "Roof status; lineup confirmation.",
      "result": null,
      "profit_units": 0.0,
      "clv": null,
      "closing_line": null,
      "parse_warning": null,
      "graded_at": "2026-06-16T09:06:08Z"
    },
    {
      "game_id": "38a1ef501107d0410c8595f25612567d",
      "matchup": "LAA @ AZ",
      "away_abbr": "LAA",
      "home_abbr": "AZ",
      "action": "pass",
      "pick_raw": "PASS",
      "pick_side": null,
      "pick_market": null,
      "price": null,
      "units": 0,
      "units_raw": "PASS",
      "edge": "none",
      "reason": "Ureña's 2.44 ERA masks a 4.19 AGG xFIP and a wild L14 (6.5 BB/9) — a regression candidate I won't back. Nelson (4.46 AGG xFIP) is similarly mediocre. AZ -130 prices ~57% at home vs weak LAA offense; my number sits within 3 pts. Pass.",
      "data_gap": "Roof status (affects total more than side).",
      "result": null,
      "profit_units": 0.0,
      "clv": null,
      "closing_line": null,
      "parse_warning": null,
      "graded_at": "2026-06-16T09:06:08Z"
    },
    {
      "game_id": "8e54fa4eee405d90f575942ad15b1d52",
      "matchup": "PIT @ ATH",
      "away_abbr": "PIT",
      "home_abbr": "ATH",
      "action": "pass",
      "pick_raw": "PASS",
      "pick_side": null,
      "pick_market": null,
      "price": null,
      "units": 0,
      "units_raw": "PASS",
      "edge": "none",
      "reason": "Ginn (3.78 AGG xFIP, 14.7 K-BB%) modestly outclasses Jones (4.26, tiny sample), but Sutter Health is a 121-runs park making margin highly variable — exactly the high-variance spot I avoid for sides. ATH -125 prices ~55%; my read sits near there. Pass the side; lean Over on environment.",
      "data_gap": "Jones has only 9.1 AGG IP — thin true-talent read.",
      "result": null,
      "profit_units": 0.0,
      "clv": null,
      "closing_line": null,
      "parse_warning": null,
      "graded_at": "2026-06-16T09:06:08Z"
    },
    {
      "game_id": "da125dfa2d7fe97d5836e50dd394db59",
      "matchup": "TB @ LAD",
      "away_abbr": "TB",
      "home_abbr": "LAD",
      "action": "bet",
      "pick_raw": "LAD ML",
      "pick_side": "home",
      "pick_market": "ml",
      "price": -164,
      "units": 1,
      "units_raw": "1",
      "edge": "5.0 pts",
      "reason": "Martinez carries a deceptive 2.43 ERA over a 4.45 AGG xFIP/4.55 SIERA and a disastrous L14 (2.5 K/9, 6.59 SIERA) — a prime regression candidate now facing the league's best offense (110 wRC+ vs RHP, +141 run diff, Ohtani/Freeman/Rushing). Lauer is also poor but LAD's elite offense and clearly superior bullpen (Scott/Vesia/Treinen vs TB's worn Baker/Kimbrel) tilt this further than -164. I estimate LAD ~67% vs implied ~62%, a 5-pt edge; capped at 1 unit since both starters carry small-sample L14 noise.",
      "data_gap": "Confirmed lineups (Ohtani/Freeman in).",
      "result": "win",
      "profit_units": 0.6098,
      "clv": 0,
      "closing_line": -164,
      "parse_warning": null,
      "graded_at": "2026-06-16T09:06:08Z"
    }
  ],
  "parlay": null,
  "best_bet": null,
  "best_bet_skip": true,
  "best_bet_skip_reason": "no 3-unit play identified",
  "counts": {
    "games": 10,
    "bets": 1,
    "leans": 0,
    "passes": 9,
    "units_risked": 1,
    "parlay_units": 0
  },
  "graded_at": "2026-06-16T09:06:08Z"
}